pyzw/Dm大漠命令.py
pyzw/EXE打包命令.py
pyzw/Excel表格命令.py
pyzw/HTTP请求命令.py
pyzw/OCR命令.py
pyzw/PPT演示命令.py
pyzw/Tk界面命令.py
pyzw/Word文档命令.py
pyzw/__init__.py
pyzw/内存命令.py
pyzw/内置命令.py
pyzw/列表命令.py
pyzw/剪切板命令.py
pyzw/图片命令.py
pyzw/字符串命令.py
pyzw/字节串命令.py
pyzw/打包命令.py
pyzw/数据库命令.py
pyzw/文件命令.py
pyzw/时间命令.py
pyzw/校验命令.py
pyzw/目录命令.py
pyzw/窗口命令.py
pyzw/系统命令.py
pyzw/线程命令.py
pyzw/编码命令.py
pyzw/运算命令.py
pyzw/进程命令.py
pyzw/键盘命令.py
pyzw/颜色命令.py
pyzw/鼠标命令.py
pyzw-0.0.15.dist-info/METADATA
pyzw-0.0.15.dist-info/WHEEL
pyzw-0.0.15.dist-info/top_level.txt
pyzw-0.0.15.dist-info/RECORD
