Metadata-Version: 2.1
Name: pyzw
Version: 0.0.15
Summary: Python中文库（PyZW）是基于Python标准库和诸多第三方库再次封装的中文模块，其函数命令超过1000个，涵盖了人工智能、前后台键鼠操作、找图找色、网页自动化、手机自动化、OCR、YOLO、OpenCV、Word文档、Excel表格、PPT演示等多个领域。
Home-page: https://github.com/XueLiren/PyZW
Author: XueLiren
Author-email: liren1029@gmail.com
License: Apache Software License 2.0
Classifier: Development Status :: 4 - Beta
Classifier: Intended Audience :: Developers
Classifier: Topic :: Software Development :: Testing
Classifier: Programming Language :: Python
Classifier: Programming Language :: Python :: 3
Classifier: Programming Language :: Python :: 3.7
Classifier: Programming Language :: Python :: 3.8
Classifier: Programming Language :: Python :: 3.9
Classifier: Programming Language :: Python :: 3.10
Classifier: Programming Language :: Python :: 3.11
Classifier: Programming Language :: Python :: 3 :: Only
Classifier: Programming Language :: Python :: Implementation :: CPython
Classifier: Programming Language :: Python :: Implementation :: PyPy
Classifier: Operating System :: OS Independent
Classifier: License :: OSI Approved :: Apache Software License
Requires-Python: >=3.7
